XSBCK/__XSBCKParams.py
XSBCK/__XZarr.py
XSBCK/__correction.py
XSBCK/__curses_doc.py
XSBCK/__doc.py
XSBCK/__exceptions.py
XSBCK/__exec.py
XSBCK/__init__.py
XSBCK/__io.py
XSBCK/__logs.py
XSBCK/__release.py
XSBCK/__utils.py
XSBCK-1.0.0.data/scripts/xsbck
XSBCK-1.0.0.dist-info/LICENSE
XSBCK-1.0.0.dist-info/METADATA
XSBCK-1.0.0.dist-info/WHEEL
XSBCK-1.0.0.dist-info/top_level.txt
XSBCK-1.0.0.dist-info/RECORD
